[
    { "name": "Alabama", "region": "South", "original": false},
    { "name": "Alaska", "region": "Pacific", "original": false},
    { "name": "Arizona", "region": "Mountain", "original": false},
    { "name": "Arkansas", "region": "South", "original": false},
    { "name": "California", "region": "Pacific", "original": false},
    { "name": "Colorado", "region": "Mountain", "original": false},
    { "name": "Connecticut", "region": "New England", "original": true},
    { "name": "Delaware", "region": "South", "original": true},
    { "name": "Florida", "region": "South", "original": false},
    { "name": "Georgia", "region": "South", "original": true},
    { "name": "Hawaii", "region": "Pacific", "original": false},
    { "name": "Idaho", "region": "Mountain", "original": false},
    { "name": "Illinois", "region": "Midwest", "original": false},
    { "name": "Indiana", "region": "Midwest", "original": false},
    { "name": "Iowa", "region": "Midwest", "original": false},
    { "name": "Kansas", "region": "Midwest", "original": false},
    { "name": "Kentucky", "region": "South", "original": false},
    { "name": "Louisiana", "region": "South", "original": false},
    { "name": "Maine", "region": "New England", "original": false},
    { "name": "Maryland", "region": "South", "original": true},
    { "name": "Massachusetts", "region": "New England", "original": true},
    { "name": "Michigan", "region": "Midwest", "original": false},
    { "name": "Minnesota", "region": "Midwest", "original": false},
    { "name": "Mississippi", "region": "South", "original": false},
    { "name": "Missouri", "region": "Midwest", "original": false},
    { "name": "Montana", "region": "Mountain", "original": false},
    { "name": "Nebraska", "region": "Midwest", "original": false},
    { "name": "Nevada", "region": "Mountain", "original": false},
    { "name": "New Hampshire", "region": "New England", "original": true},
    { "name": "New Jersey", "region": "Mid-Atlantic", "original": true},
    { "name": "New Mexico", "region": "Mountain", "original": false},
    { "name": "New York", "region": "Mid-Atlantic", "original": true},
    { "name": "North Carolina", "region": "South", "original": true},
    { "name": "North Dakota", "region": "Midwest", "original": false},
    { "name": "Ohio", "region": "Midwest", "original": false},
    { "name": "Oklahoma", "region": "South", "original": false},
    { "name": "Oregon", "region": "Pacific", "original": false},
    { "name": "Pennsylvania", "region": "Mid-Atlantic", "original": true},
    { "name": "Rhode Island", "region": "New England", "original": true},
    { "name": "South Carolina", "region": "South", "original": true},
    { "name": "South Dakota", "region": "Midwest", "original": false},
    { "name": "Tennessee", "region": "South", "original": false},
    { "name": "Texas", "region": "South", "original": false},
    { "name": "Utah", "region": "Mountain", "original": false},
    { "name": "Vermont", "region": "New England", "original": false},
    { "name": "Virginia", "region": "South", "original": true},
    { "name": "Washington", "region": "Pacific", "original": false},
    { "name": "West Virginia", "region": "South", "original": false},
    { "name": "Wisconsin", "region": "Midwest", "original": false},
    { "name": "Wyoming", "region": "Mountain", "original": false}
]
